[
  {
    "date": "April 2026",
    "headline": "The American West's water crisis has a governance problem",
    "organization": "Stanford Woods Institute for the Environment",
    "link": "https://woods.stanford.edu/news/american-wests-water-crisis-has-governance-problem"
  },
  {
    "date": "April 2026",
    "headline": "Corisa Wong's Dissertation Defense",
    "organization": "Stanford University",
    "link": "https://www.linkedin.com/feed/update/urn:li:activity:7445158056277204992"
  },
  {
    "date": "March 2026",
    "headline": "Strategic water utilities are starting to see the coupling of water and energy systems as an asset rather than a liability",
    "organization": "Smart Water Magazine",
    "link": "https://issuu.com/smart-water-magazine/docs/smart_water_magazine_print_edition_29/79"
  },
  {
    "date": "March 2026",
    "headline": "Gina Kittleson named a 2026 Rising Environmental Leader",
    "organization": "Stanford Woods Institute for the Environment",
    "link": "https://woods.stanford.edu/news/meet-2026-rising-environmental-leaders"
  }
]
